swarm_cid/Exceptions.py
swarm_cid/__init__.py
swarm_cid/py.typed
swarm_cid/swarm_cid.py
swarm_cid/types.py
swarm_cid_py-0.1.3.dist-info/LICENSE.txt
swarm_cid_py-0.1.3.dist-info/METADATA
swarm_cid_py-0.1.3.dist-info/WHEEL
swarm_cid_py-0.1.3.dist-info/RECORD
