Metadata-Version: 2.1
Name: swarm-cid-py
Version: 0.1.3
Summary: Utility library written in Python to convert Swarm hex references into Swarm CIDs
Home-page: https://github.com/Aviksaikat/swarm-cid-py
License: AGPL-3.0-or-later
Author: SAIKAT KARMAKAR
Author-email: saikickkarma@protonmail.com
Requires-Python: >=3.9,<4.0
Classifier: License :: OSI Approved :: GNU Affero General Public License v3 or later (AGPLv3+)
Classifier: Programming Language :: Python :: 3
Classifier: Programming Language :: Python :: 3.9
Classifier: Programming Language :: Python :: 3.10
Classifier: Programming Language :: Python :: 3.11
Requires-Dist: multiformats-fix (>=0.2.2,<0.3.0)
Requires-Dist: py-multiformats-cid (>=0.4.4,<0.5.0)
Requires-Dist: safe-pysha3 (>=1.0.4,<2.0.0)
